zlogging/__init__.py
zlogging/_aux.py
zlogging/_compat.py
zlogging/_data.py
zlogging/_exc.py
zlogging/_gen.py
zlogging/_typing.py
zlogging/dumper.py
zlogging/loader.py
zlogging/model.py
zlogging/types.py
zlogging/typing.py
zlogging/enum/__init__.py
zlogging/enum/af_packet.py
zlogging/enum/broker.py
zlogging/enum/cluster.py
zlogging/enum/dce_rpc.py
zlogging/enum/http.py
zlogging/enum/input.py
zlogging/enum/intel.py
zlogging/enum/json.py
zlogging/enum/known.py
zlogging/enum/log.py
zlogging/enum/management.py
zlogging/enum/management_controller_runtime.py
zlogging/enum/management_log.py
zlogging/enum/mount3.py
zlogging/enum/mqtt.py
zlogging/enum/net_control.py
zlogging/enum/nfs3.py
zlogging/enum/notice.py
zlogging/enum/open_flow.py
zlogging/enum/pcap.py
zlogging/enum/protocol_detector.py
zlogging/enum/reporter.py
zlogging/enum/signatures.py
zlogging/enum/smb.py
zlogging/enum/socks.py
zlogging/enum/software.py
zlogging/enum/ssl.py
zlogging/enum/sum_stats.py
zlogging/enum/supervisor.py
zlogging/enum/telemetry.py
zlogging/enum/tunnel.py
zlogging/enum/weird.py
zlogging/enum/zeek.py
zlogging/enum/zeekygen_example.py
zlogging-0.1.3.post5.dist-info/LICENSE
zlogging-0.1.3.post5.dist-info/METADATA
zlogging-0.1.3.post5.dist-info/WHEEL
zlogging-0.1.3.post5.dist-info/entry_points.txt
zlogging-0.1.3.post5.dist-info/top_level.txt
zlogging-0.1.3.post5.dist-info/RECORD
