Metadata-Version: 2.1
Name: zlogging
Version: 0.1.3.post5
Summary: zlogging: Bro/Zeek logging framework for Python.
Author-email: Jarry Shaw <jarryshaw@icloud.com>
Maintainer: Jarry Shaw
License: BSD 3-Clause License
Project-URL: homepage, https://jarryshaw.github.io/zlogging/
Project-URL: documentation, https://jarryshaw.github.io/zlogging/
Project-URL: repository, https://github.com/JarryShaw/zlogging
Project-URL: changelog, https://github.com/JarryShaw/zlogging/releases
Keywords: bro,zeek,logging
Classifier: Development Status :: 5 - Production/Stable
Classifier: Intended Audience :: Developers
Classifier: License :: OSI Approved :: BSD License
Classifier: Natural Language :: English
Classifier: Operating System :: OS Independent
Classifier: Programming Language :: Python
Classifier: Topic :: Software Development
Classifier: Topic :: Utilities
Requires-Python: <4,>=3.6
License-File: LICENSE
Requires-Dist: typing-inspect
Requires-Dist: typing-extensions
Requires-Dist: bpc-f2format ; python_version < "3.6"
Requires-Dist: dataclasses ; python_version < "3.7"
Requires-Dist: aenum ; python_version < "3.7"
Requires-Dist: bpc-poseur ; python_version < "3.8"
Requires-Dist: bpc-walrus ; python_version < "3.8"
Provides-Extra: docs
Requires-Dist: Sphinx >=6.1.3 ; extra == 'docs'
Requires-Dist: sphinx-autodoc-typehints ; extra == 'docs'
Requires-Dist: sphinx-opengraph ; extra == 'docs'
Requires-Dist: sphinx-copybutton ; extra == 'docs'
Requires-Dist: furo ; extra == 'docs'
